tutor_contrib_let-19.0.0.dist-info/licenses/LICENSE.txt
tutorlet/__about__.py
tutorlet/__init__.py
tutorlet/plugin.py
tutorlet/patches/.gitignore
tutorlet/patches/caddyfile
tutorlet/patches/common-env-features
tutorlet/patches/discovery-common-settings
tutorlet/patches/mfe-dockerfile-pre-npm-build-authn
tutorlet/patches/openedx-auth
tutorlet/patches/openedx-cms-common-settings
tutorlet/patches/openedx-common-settings
tutorlet/patches/openedx-dockerfile-post-git-checkout
tutorlet/patches/openedx-lms-common-settings
tutorlet/patches/openedx-lms-production-settings
tutorlet/templates/let/apps/.gitignore
tutorlet/templates/let/build/.gitignore
tutorlet/templates/let/tasks/lms/.gitignore
tutorlet/templates/let/tasks/lms/init
tutor_contrib_let-19.0.0.dist-info/METADATA
tutor_contrib_let-19.0.0.dist-info/WHEEL
tutor_contrib_let-19.0.0.dist-info/entry_points.txt
tutor_contrib_let-19.0.0.dist-info/top_level.txt
tutor_contrib_let-19.0.0.dist-info/RECORD
