Metadata-Version: 2.4
Name: tutor-contrib-let
Version: 19.0.0
Summary: Tutor plugin to simplify the configuration of Open edX settings.
Home-page: https://github.com/aulasneo/tutor-contrib-let
Author: Andrés González
Author-email: andres@aulasneo.com
License: AGPLv3
Project-URL: Code, https://github.com/aulasneo/tutor-contrib-let
Project-URL: Issue tracker, https://github.com/aulasneo/tutor-contrib-let/issues
Classifier: Development Status :: 3 - Alpha
Classifier: Intended Audience :: Developers
Classifier: License :: OSI Approved :: GNU Affero General Public License v3
Classifier: Operating System :: OS Independent
Classifier: Programming Language :: Python
Classifier: Programming Language :: Python :: 3.8
Classifier: Programming Language :: Python :: 3.9
Classifier: Programming Language :: Python :: 3.10
Classifier: Programming Language :: Python :: 3.11
Classifier: Programming Language :: Python :: 3.12
Requires-Python: >=3.11
License-File: LICENSE.txt
Requires-Dist: tutor<20.0.0,>=19.0.0
Requires-Dist: tabulate<1.0.0,>=0.9.0
Provides-Extra: dev
Requires-Dist: tutor[dev]<20.0.0,>=19.0.0; extra == "dev"
Dynamic: author
Dynamic: author-email
Dynamic: classifier
Dynamic: description
Dynamic: description-content-type
Dynamic: home-page
Dynamic: license
Dynamic: license-file
Dynamic: project-url
Dynamic: provides-extra
Dynamic: requires-dist
Dynamic: requires-python
Dynamic: summary
